CHANGELOG.rst
LICENSE
MANIFEST.in
README.rst
pyproject.toml
setup.cfg
setup.py
tox.ini
docs/.gitignore
docs/Makefile
docs/conf.py
docs/index.rst
src/cachetools/__init__.py
src/cachetools/cache.py
src/cachetools/fifo.py
src/cachetools/func.py
src/cachetools/keys.py
src/cachetools/lfu.py
src/cachetools/lru.py
src/cachetools/mru.py
src/cachetools/rr.py
src/cachetools/ttl.py
src/cachetools_chrisglass.egg-info/PKG-INFO
src/cachetools_chrisglass.egg-info/SOURCES.txt
src/cachetools_chrisglass.egg-info/dependency_links.txt
src/cachetools_chrisglass.egg-info/top_level.txt
tests/__init__.py
tests/test_aio_function.py
tests/test_aio_method.py
tests/test_cache.py
tests/test_deprecated.py
tests/test_fifo.py
tests/test_func.py
tests/test_keys.py
tests/test_lfu.py
tests/test_lru.py
tests/test_method.py
tests/test_mru.py
tests/test_rr.py
tests/test_ttl.py
tests/test_wrapper.py